AUTHORS.rst
CONTRIBUTING.rst
LICENSE.txt
MANIFEST.in
README.rst
_version.py
pyproject.toml
setup.cfg
setup.py
versioneer.py
cyminmax.egg-info/PKG-INFO
cyminmax.egg-info/SOURCES.txt
cyminmax.egg-info/dependency_links.txt
cyminmax.egg-info/not-zip-safe
cyminmax.egg-info/requires.txt
cyminmax.egg-info/top_level.txt
docs/Makefile
docs/api.rst
docs/authors.rst
docs/conf.py
docs/contributing.rst
docs/index.rst
docs/installation.rst
docs/make.bat
docs/readme.rst
docs/usage.rst
src/cyminmax.pxd
src/cyminmax.pyx
tests/__init__.py
tests/test_cyminmax.py